{
    "oracle19c"                         : {
      "oracle"                          : {
        "user"                          : "SYSTEM"
      , "password"                      : "oracle"
      , "connectString"                 : "ORCL19c"
      }
    },
    "oracle18c"                         : {
      "oracle"                          : {
        "user"                          : "SYSTEM"
      , "password"                      : "oracle"
      , "connectString"                 : "ORCL18c"
      }
    },
    "oracle12c"           : {
      "oracle"                          : {
        "user"                          : "SYSTEM"
      , "password"                      : "oracle"
      , "connectString"                 : "ORCL12c"
      }
    },
    "oracle11g"           : {
      "oracle"                          : {
        "user"                          : "SYSTEM"
      , "password"                      : "oracle"
      , "connectString"                 : "ORCL11g"
      }
    },
    "mssql17"                           : {
      "mssql"                           : {  
        "user"                          : "sa"
      , "server"                        : "yadamu-db1"
      , "database"                      : "master"
      , "password"                      : "oracle#1"
      , "requestTimeout"                : 360000000
      , "options"                       : {
          "encrypt"                     : false 
        , "abortTransactionOnError"     : false
        }
      }
    },
    "mssql19"                           : {
      "mssql"                           : {  
        "user"                          : "sa"
      , "server"                        : "yadamu-db1"
      , "database"                      : "master"
      , "password"                      : "oracle#1"
      , "requestTimeout"                : 360000000
      , "options"                       : {
          "encrypt"                     : false 
        , "abortTransactionOnError"     : false
        }
      }
    },
    "postgres#1"                        : {
      "postgres"                        : {
        "user"                          : "postgres"
      , "host"                          : "yadamu-db1"
      , "database"                      : "yadamu"
      , "password"                      : "oracle"
      , "port"                          : 5432
      }
    },
    "mysql#1"                           : {
      "mysql"                           : {          
        "user"                          : "root"
      , "host"                          : "yadamu-db1"
      , "database"                      : "sys"
      , "password"                      : "oracle"
      , "port"                          : 3306
      , "multipleStatements"            : true
      , "typeCast"                      : true
      , "supportBigNumbers"             : true
      , "bigNumberStrings"              : true          
      , "dateStrings"                   : true
      }
    },
    "mariadb#1"                         : {
      "mariadb"                         : {
        "user"                          : "root"
      , "host"                          : "yadamu-db1"
      , "database"                      : "mysql"
      , "password"                      : "oracle"
      , "port"                          : 3307
      , "multipleStatements"            : true
      , "typeCast"                      : true
      , "supportBigNumbers"             : true
      , "bigNumberStrings"              : true          
      , "dateStrings"                   : true 
      }
    },
    "mongodb#1"                         : {
      "mongodb"                         : {
        "host"                          : "yadamu-db1"
      , "port"                          : 27017
      , "options"                       : {
           "socketTimeoutMS"            : 900000
        }
      }
    },
    "minio#1"                           : {
	  "awsS3"                           : {
          "accessKeyId"                 : "AKIAIOSFODNN7EXAMPLE" ,
          "secretAccessKey"             : "wJalrXUtnFEMI/K7MDENG/bPxRfiCYEXAMPLEKEY" ,
          "endpoint"                    : "http://yadamu-db1:9000" ,
          "s3ForcePathStyle"            : true,
          "signatureVersion"            : "v4"
      }
	},
    "load-scratch"                            : {
	  "loader"                          : {
		"directory"                     : "scratch" 
      }
	},
    "file-connection"                   : {
      "file"                            : {
		"directory"                     : "JSON/%connection%" 
      }
    },
    "file-connection-mode"              : {
      "file"                            : {
		"directory"                     : "JSON/%connection%/%mode%" 
      }
    },
    "file-vendor"                       : {
      "file"                            : {
		"directory"                     : "JSON/%vendor%" 
      }
    },
    "file-oracle19c-mode"               : {
      "file"                            : {
		"directory"                     : "JSON/oracle19c/%mode%" 
      }
    },
    "file-mssql19"                      : {
      "file"                            : {
		"directory"                     : "JSON/mssql19" 
      }
    },
    "file-mysql"                       : {
      "file"                            : {
		"directory"                     : "JSON/mysql" 
      }
    },
    "file-JSON-root"                    : {
      "file"                            : {
		"directory"                     : "JSON" 
      }
	},
    "scratch"                           : {
      "file"                            : {
		"directory"                     : "scratch" 
      }
    }}
