{  "drivers"                   : {    "file"                    : "../../file/node/fileQA.js"   ,"oracle"                  : "../../oracle/node/oracleQA.js"   ,"postgres"                : "../../postgres/node/postgresQA.js"   ,"mssql"                   : "../../mssql/node/mssqlQA.js"   ,"mysql"                   : "../../mysql/node/mysqlQA.js"   ,"mariadb"                 : "../../mariadb/node/mariadbQA.js"   ,"mongodb"                 : "../../mongodb/node/mongoQA.js"   ,"snowflake"               : "../../snowflake/node/snowflakeQA.js"   ,"teradata"                : "../../teradata/node/teradataQA.js"  }, "mariadb"                   : {    "TIMESTAMP_PRECISION"     : 6  }, "mongodb"                   : {  }, "mssql"                     : {    "STRIP_XML_DECLARATION"   : true  , "TIMESTAMP_PRECISION"     : 9  }, "mysql"                     : {    "TIMESTAMP_PRECISION"     : 6  }, "oracle"                    : {    "EMPTY_STRING_IS_NULL"    : true  , "TIMESTAMP_PRECISION"     : 9  }, "postgres"                  : {    "TIMESTAMP_PRECISION"     : 6  }, "snowflake"                 : {  }, "SPATIAL_PRECISION"         : {    "default"                 : 18  , "mssql"                   : { "oracle": 10}  , "mysql"                   : { "oracle" : 10}  , "mariadb"                 : { "oracle" : 10}  }, "ORDERED_JSON"              : {    "default"                 : false  , "oracle"                  : { "oracle#20": true}  }, "XSL_TRANSFORMATION"        : {    "default"                 : null  , "oracle"                  : { "snowflake": "SNOWFLAKE.XSL"}  }, "DDL_SUPPORTED"             : ["oracle"], "SCHEMA_MAPPINGS"           : {    "snowflake"               : {      "HR"                    : {        "database"            : "ORACLE"      , "schema"              : "HR"      }    , "HR1"                   : {        "database"            : "ORACLE"      , "schema"              : "HR1"      }    , "SH"                    : {        "database"            : "ORACLE"      , "schema"              : "SH"      }    , "SH1"                   : {        "database"            : "ORACLE"      , "schema"              : "SH1"      }    , "OE"                    : {        "database"            : "ORACLE"      , "schema"              : "OE"      }    , "OE1"                   : {        "database"            : "ORACLE"      , "schema"              : "OE1"      }    , "PM"                    : {        "database"            : "ORACLE"      , "schema"              : "PM"      }    , "PM1"                   : {        "database"            : "ORACLE"      , "schema"              : "PM1"      }    , "IX"                   : {        "database"            : "ORACLE"      , "schema"              : "IX"      }    , "IX1"                   : {        "database"            : "ORACLE"      , "schema"              : "IX1"      }    , "BI"                    : {        "database"            : "ORACLE"      , "schema"              : "BI"      }    , "BI1"                    : {        "database"            : "ORACLE"      , "schema"              : "BI1"      }    , "jtest"                 : {        "database"            : "MYSQL"      , "schema"              : "jtest"      }    , "sakila"                : {        "database"            : "MYSQL"      , "schema"              : "sakila"      }    , "Northwind"            : {        "database"            : "MSSQL"      , "schema"              : "Northwind"      }    , "Person"                : {        "database"            : "MSSQL"      , "schema"              : "Person"      }    }  }}